{"provides":{"DateTime::LeapSecond":{"version":"0.72","file":"DateTime/LeapSecond.pm"},"DateTime":{"version":"0.72","file":"DateTime.pm"},"DateTime::Infinite::Future":{"version":"0.72","file":"DateTime/Infinite.pm"},"DateTime::Helpers":{"version":"0.72","file":"DateTime/Helpers.pm"},"DateTime::Duration":{"version":"0.72","file":"DateTime/Duration.pm"},"DateTime::Infinite::Past":{"version":"0.72","file":"DateTime/Infinite.pm"},"DateTime::Infinite":{"version":"0.72","file":"DateTime/Infinite.pm"}},"version":"0.72","name":"DateTime","dist":"DateTime-0.72","pathname":"D/DR/DROLSKY/DateTime-0.72.tar.gz","module":"DateTime"}