{"provides":{"Catalyst::ClassData":{"file":"Catalyst/ClassData.pm"},"Catalyst::DispatchType::Regex":{"file":"Catalyst/DispatchType/Regex.pm"},"Catalyst::Dispatcher":{"file":"Catalyst/Dispatcher.pm"},"Catalyst::EngineLoader":{"file":"Catalyst/EngineLoader.pm"},"Catalyst::Base":{"file":"Catalyst/Base.pm"},"Catalyst::Log":{"file":"Catalyst/Log.pm"},"Catalyst::Component::ContextClosure":{"file":"Catalyst/Component/ContextClosure.pm"},"Catalyst::DispatchType::Default":{"file":"Catalyst/DispatchType/Default.pm"},"Catalyst::ScriptRole":{"file":"Catalyst/ScriptRole.pm"},"Catalyst":{"version":"5.90007","file":"Catalyst.pm"},"Catalyst::Script::CGI":{"file":"Catalyst/Script/CGI.pm"},"Catalyst::Model":{"file":"Catalyst/Model.pm"},"Catalyst::Action":{"file":"Catalyst/Action.pm"},"Catalyst::Controller":{"file":"Catalyst/Controller.pm"},"Catalyst::Utils":{"file":"Catalyst/Utils.pm"},"Catalyst::DispatchType::Chained":{"file":"Catalyst/DispatchType/Chained.pm"},"Catalyst::Exception::Go":{"file":"Catalyst/Exception/Go.pm"},"Catalyst::Test":{"file":"Catalyst/Test.pm"},"Catalyst::Component":{"file":"Catalyst/Component.pm"},"Catalyst::View":{"file":"Catalyst/View.pm"},"Catalyst::Request::Upload":{"file":"Catalyst/Request/Upload.pm"},"Catalyst::Response":{"file":"Catalyst/Response.pm"},"Catalyst::ActionChain":{"file":"Catalyst/ActionChain.pm"},"Catalyst::Exception":{"file":"Catalyst/Exception.pm"},"Catalyst::Script::Server":{"file":"Catalyst/Script/Server.pm"},"Catalyst::Script::Test":{"file":"Catalyst/Script/Test.pm"},"Catalyst::Script::Create":{"file":"Catalyst/Script/Create.pm"},"Catalyst::Script::FastCGI":{"file":"Catalyst/Script/FastCGI.pm"},"Catalyst::ScriptRunner":{"file":"Catalyst/ScriptRunner.pm"},"Catalyst::DispatchType::Path":{"file":"Catalyst/DispatchType/Path.pm"},"Catalyst::ActionContainer":{"file":"Catalyst/ActionContainer.pm"},"Catalyst::Exception::Base":{"file":"Catalyst/Exception.pm"},"Catalyst::Exception::Detach":{"file":"Catalyst/Exception/Detach.pm"},"Catalyst::Component::ApplicationAttribute":{"file":"Catalyst/Component/ApplicationAttribute.pm"},"Catalyst::Request":{"file":"Catalyst/Request.pm"},"Catalyst::Exception::Basic":{"file":"Catalyst/Exception/Basic.pm"},"Catalyst::Engine":{"file":"Catalyst/Engine.pm"},"Catalyst::DispatchType::Index":{"file":"Catalyst/DispatchType/Index.pm"},"Catalyst::Exception::Interface":{"file":"Catalyst/Exception/Interface.pm"},"Catalyst::Runtime":{"version":"5.90007","file":"Catalyst/Runtime.pm"},"Catalyst::Stats":{"file":"Catalyst/Stats.pm"},"Catalyst::DispatchType":{"file":"Catalyst/DispatchType.pm"}},"version":"5.90007","name":"Catalyst::Runtime","dist":"Catalyst-Runtime-5.90007","pathname":"B/BO/BOBTFISH/Catalyst-Runtime-5.90007.tar.gz","module":"Catalyst"}